mderic_djawin/__init__.py
mderic_djawin/cli.py
mderic_djawin-0.1.1.dist-info/METADATA
mderic_djawin-0.1.1.dist-info/WHEEL
mderic_djawin-0.1.1.dist-info/entry_points.txt
mderic_djawin-0.1.1.dist-info/top_level.txt
mderic_djawin-0.1.1.dist-info/RECORD
