Metadata-Version: 2.4
Name: mderic_djawin
Version: 0.1.1
Summary: A CLI to automate Django project setup with virtualenv.
Author-email: mucodevde <mucodevde@gmail.com>
Classifier: License :: OSI Approved :: MIT License
Requires-Python: >=3.6
